{
  "data": {
    "type": "Spawn",
    "biomes": []
  },
  "textures": [
    {
      "name": "spawnmart.png"
    }
  ],
  "names": [
    {
      "name": "Shopkeeper"
    }
  ],
  "chat": [
    {
      "hello": "Hi! Wanna buy some items?",
      "goodbye": "Come back soon!"
    }
  ],
  "items": [
    {
      "name": "pixelmon:mint_hardy",
      "variation": false
    },
    {
      "name": "pixelmon:mint_serious",
      "variation": false
    },
    {
      "name": "pixelmon:mint_docile",
      "variation": false
    },
    {
      "name": "pixelmon:mint_bashful",
      "variation": false
    },
    {
      "name": "pixelmon:mint_quirky",
      "variation": false
    },
    {
      "name": "pixelmon:mint_lonely",
      "variation": false
    },
    {
      "name": "pixelmon:mint_naughty",
      "variation": false
    },
    {
      "name": "pixelmon:mint_bold",
      "variation": false
    },
    {
      "name": "pixelmon:mint_relaxed",
      "variation": false
    },
    {
      "name": "pixelmon:mint_impish",
      "variation": false
    },
    {
      "name": "pixelmon:mint_lax",
      "variation": false
    },
    {
      "name": "pixelmon:mint_hasty",
      "variation": false
    },
    {
      "name": "pixelmon:mint_naive",
      "variation": false
    },
    {
      "name": "pixelmon:mint_mild",
      "variation": false
    },
    {
      "name": "pixelmon:mint_quiet",
      "variation": false
    },
    {
      "name": "pixelmon:mint_rash",
      "variation": false
    },
    {
      "name": "pixelmon:mint_calm",
      "variation": false
    },
    {
      "name": "pixelmon:mint_gentle",
      "variation": false
    },
    {
      "name": "pixelmon:mint_sassy",
      "variation": false
    },
    {
      "name": "pixelmon:mint_careful",
      "variation": false
    },
    {
      "name": "pixelmon:mint_modest",
      "variation": false
    },
    {
      "name": "pixelmon:mint_jolly",
      "variation": false
    },
    {
      "name": "pixelmon:mint_timid",
      "variation": false
    },
    {
      "name": "pixelmon:mint_adamant",
      "variation": false
    },
    {
      "name": "pixelmon:mint_brave",
      "variation": false
    }
}
